wpbiff/__about__.py
wpbiff/__init__.py
wpbiff/cli.py
wpbiff/core/__init__.py
wpbiff/core/brutesession.py
wpbiff/core/wpauthenticator.py
wpbiff/plugins/__init__.py
wpbiff/plugins/ga.py
wpbiff/plugins/wpga.py
wpbiff-0.1.1.dist-info/top_level.txt
wpbiff-0.1.1.dist-info/entry_points.txt
wpbiff-0.1.1.dist-info/METADATA
wpbiff-0.1.1.dist-info/DESCRIPTION.rst
wpbiff-0.1.1.dist-info/metadata.json
wpbiff-0.1.1.dist-info/WHEEL
wpbiff-0.1.1.dist-info/RECORD
