Metadata-Version: 2.0
Name: wpbiff
Version: 0.1.1
Summary: Wordpress Two-Factor Authentication Brute-forcer
Home-page: https://github.com/gszathmari/wpbiff
Author: Gabor Szathmari
Author-email: gszathmari@gmail.com
License: MIT
Keywords: security password
Platform: Linux
Classifier: Development Status :: 4 - Beta
Classifier: License :: OSI Approved :: MIT License
Classifier: Topic :: Security
Classifier: Intended Audience :: Other Audience
Classifier: Programming Language :: Python :: 2 :: Only
Classifier: Programming Language :: Python :: 2.6
Classifier: Programming Language :: Python :: 2.7
Requires-Dist: click
Requires-Dist: colorama
Requires-Dist: progressbar
Requires-Dist: requests
